{
  "truth": "wall.v1",
  "drawing_id": "0010",
  "walls": [
    {
      "id": "w1",
      "axis": [
        [
          0.0,
          0.0
        ],
        [
          8000.0,
          0.0
        ]
      ],
      "thickness": 100.0,
      "layer": "WALL",
      "handles": [
        "32",
        "33"
      ]
    },
    {
      "id": "w2",
      "axis": [
        [
          8000.0,
          0.0
        ],
        [
          8000.0,
          6000.0
        ]
      ],
      "thickness": 300.0,
      "layer": "WALL",
      "handles": [
        "34",
        "35"
      ]
    },
    {
      "id": "w3",
      "axis": [
        [
          8000.0,
          6000.0
        ],
        [
          0.0,
          6000.0
        ]
      ],
      "thickness": 240.0,
      "layer": "WALL",
      "handles": [
        "36",
        "37"
      ]
    },
    {
      "id": "w4",
      "axis": [
        [
          0.0,
          6000.0
        ],
        [
          0.0,
          0.0
        ]
      ],
      "thickness": 200.0,
      "layer": "WALL",
      "handles": [
        "38",
        "39"
      ]
    },
    {
      "id": "w5",
      "axis": [
        [
          3776.0,
          0.0
        ],
        [
          3776.0,
          6000.0
        ]
      ],
      "thickness": 150.0,
      "layer": "WALL",
      "handles": [
        "3A",
        "3B"
      ]
    },
    {
      "id": "w6",
      "axis": [
        [
          3776.0,
          2386.0
        ],
        [
          8000.0,
          2386.0
        ]
      ],
      "thickness": 240.0,
      "layer": "WALL",
      "handles": [
        "3C",
        "3D"
      ]
    },
    {
      "id": "w7",
      "axis": [
        [
          0.0,
          3595.0
        ],
        [
          3776.0,
          3595.0
        ]
      ],
      "thickness": 200.0,
      "layer": "WALL",
      "handles": [
        "3E",
        "3F"
      ]
    }
  ],
  "openings": [
    {
      "id": "o1",
      "wall_id": "w1",
      "span_along_axis": [
        0.057481190383627354,
        0.20748119038362733
      ],
      "type": "window"
    },
    {
      "id": "o2",
      "wall_id": "w2",
      "span_along_axis": [
        0.3887032203271097,
        0.5887032203271098
      ],
      "type": "window"
    },
    {
      "id": "o3",
      "wall_id": "w3",
      "span_along_axis": [
        0.3514150456853406,
        0.5014150456853406
      ],
      "type": "window"
    },
    {
      "id": "o4",
      "wall_id": "w4",
      "span_along_axis": [
        0.15004171918153394,
        0.35004171918153393
      ],
      "type": "window"
    },
    {
      "id": "o5",
      "wall_id": "w5",
      "span_along_axis": [
        0.3347346564599868,
        0.5347346564599869
      ],
      "type": "window"
    },
    {
      "id": "o6",
      "wall_id": "w6",
      "span_along_axis": [
        0.2898451355535191,
        0.502913317371701
      ],
      "type": "door"
    },
    {
      "id": "o7",
      "wall_id": "w7",
      "span_along_axis": [
        0.07267124123752663,
        0.3904678514070181
      ],
      "type": "window"
    }
  ],
  "wall_handles_flat": [
    "32",
    "33",
    "34",
    "35",
    "36",
    "37",
    "38",
    "39",
    "3A",
    "3B",
    "3C",
    "3D",
    "3E",
    "3F"
  ]
}
