{
  "truth": "wall.v1",
  "drawing_id": "0016",
  "walls": [
    {
      "id": "w1",
      "axis": [
        [
          0.0,
          0.0
        ],
        [
          8000.0,
          0.0
        ]
      ],
      "thickness": 200.0,
      "layer": "WALL",
      "handles": [
        "32",
        "33"
      ]
    },
    {
      "id": "w2",
      "axis": [
        [
          8000.0,
          0.0
        ],
        [
          8000.0,
          6000.0
        ]
      ],
      "thickness": 300.0,
      "layer": "WALL",
      "handles": [
        "34",
        "35"
      ]
    },
    {
      "id": "w3",
      "axis": [
        [
          8000.0,
          6000.0
        ],
        [
          0.0,
          6000.0
        ]
      ],
      "thickness": 300.0,
      "layer": "WALL",
      "handles": [
        "36",
        "37"
      ]
    },
    {
      "id": "w4",
      "axis": [
        [
          0.0,
          6000.0
        ],
        [
          0.0,
          0.0
        ]
      ],
      "thickness": 100.0,
      "layer": "WALL",
      "handles": [
        "38",
        "39"
      ]
    },
    {
      "id": "w5",
      "axis": [
        [
          3340.0,
          0.0
        ],
        [
          3340.0,
          6000.0
        ]
      ],
      "thickness": 200.0,
      "layer": "WALL",
      "handles": [
        "3A",
        "3B"
      ]
    }
  ],
  "openings": [],
  "wall_handles_flat": [
    "32",
    "33",
    "34",
    "35",
    "36",
    "37",
    "38",
    "39",
    "3A",
    "3B"
  ]
}
