{
  "truth": "wall.v1",
  "drawing_id": "0002",
  "walls": [
    {
      "id": "w1",
      "axis": [
        [
          0.0,
          0.0
        ],
        [
          8000.0,
          0.0
        ]
      ],
      "thickness": 240.0,
      "layer": "WALL",
      "handles": [
        "50",
        "33"
      ]
    },
    {
      "id": "w2",
      "axis": [
        [
          8000.0,
          0.0
        ],
        [
          8000.0,
          6000.0
        ]
      ],
      "thickness": 240.0,
      "layer": "WALL",
      "handles": [
        "4A",
        "4E"
      ]
    },
    {
      "id": "w3",
      "axis": [
        [
          8000.0,
          6000.0
        ],
        [
          0.0,
          6000.0
        ]
      ],
      "thickness": 200.0,
      "layer": "WALL",
      "handles": [
        "36",
        "37"
      ]
    },
    {
      "id": "w4",
      "axis": [
        [
          0.0,
          6000.0
        ],
        [
          0.0,
          0.0
        ]
      ],
      "thickness": 100.0,
      "layer": "WALL",
      "handles": [
        "38",
        "39"
      ]
    },
    {
      "id": "w5",
      "axis": [
        [
          3528.0,
          0.0
        ],
        [
          3528.0,
          6000.0
        ]
      ],
      "thickness": 100.0,
      "layer": "WALL",
      "handles": [
        "4C",
        "4B"
      ]
    },
    {
      "id": "w6",
      "axis": [
        [
          3528.0,
          2230.0
        ],
        [
          8000.0,
          2230.0
        ]
      ],
      "thickness": 100.0,
      "layer": "WALL",
      "handles": [
        "3C",
        "4D"
      ]
    },
    {
      "id": "w7",
      "axis": [
        [
          0.0,
          2307.0
        ],
        [
          3528.0,
          2307.0
        ]
      ],
      "thickness": 100.0,
      "layer": "WALL",
      "handles": [
        "4F",
        "3F"
      ]
    }
  ],
  "openings": [
    {
      "id": "o1",
      "wall_id": "w1",
      "span_along_axis": [
        0.43384334199662616,
        0.5463433419966262
      ],
      "type": "door"
    },
    {
      "id": "o2",
      "wall_id": "w2",
      "span_along_axis": [
        0.3008247849838937,
        0.4508247849838937
      ],
      "type": "door"
    },
    {
      "id": "o3",
      "wall_id": "w3",
      "span_along_axis": [
        0.03424295742941622,
        0.14674295742941623
      ],
      "type": "door"
    },
    {
      "id": "o4",
      "wall_id": "w4",
      "span_along_axis": [
        0.11279353187238957,
        0.2627935318723896
      ],
      "type": "door"
    },
    {
      "id": "o5",
      "wall_id": "w5",
      "span_along_axis": [
        0.6238344808190937,
        0.7738344808190936
      ],
      "type": "door"
    },
    {
      "id": "o6",
      "wall_id": "w6",
      "span_along_axis": [
        0.4935799290725739,
        0.694832165208531
      ],
      "type": "door"
    },
    {
      "id": "o7",
      "wall_id": "w7",
      "span_along_axis": [
        0.5755195519088536,
        0.8306215927251801
      ],
      "type": "door"
    }
  ],
  "wall_handles_flat": [
    "50",
    "33",
    "4A",
    "4E",
    "36",
    "37",
    "38",
    "39",
    "4C",
    "4B",
    "3C",
    "4D",
    "4F",
    "3F"
  ]
}
